tree_sitter_slang-0.3.1.dist-info/RECORD
tree_sitter_slang-0.3.1.dist-info/WHEEL
tree_sitter_slang-0.3.1.dist-info/top_level.txt
tree_sitter_slang-0.3.1.dist-info/METADATA
tree_sitter_slang-0.3.1.dist-info/licenses/LICENSE
tree_sitter_slang/__init__.pyi
tree_sitter_slang/binding.c
tree_sitter_slang/__init__.py
tree_sitter_slang/py.typed
tree_sitter_slang/_binding.abi3.so
