Metadata-Version: 2.4
Name: tree-sitter-slang
Version: 0.3.1
Summary: Slang grammar for tree-sitter
License: MIT
Project-URL: Homepage, https://github.com/tree-sitter-grammars/tree-sitter-slang
Keywords: incremental,parsing,tree-sitter,slang
Classifier: Intended Audience :: Developers
Classifier: License :: OSI Approved :: MIT License
Classifier: Topic :: Software Development :: Compilers
Classifier: Topic :: Text Processing :: Linguistic
Classifier: Typing :: Typed
Requires-Python: >=3.10
License-File: LICENSE
Provides-Extra: core
Requires-Dist: tree-sitter>=0.25.0; extra == "core"
Dynamic: license-file
